Workbook

Sheet Business Problem
A1: Business Problem Exercise: Retail Sales Review
A3: Scenario: A regional retail manager needs to clean a small sales workbook, calculate performance metrics, identify risky orders, and prepare a print-ready summary for leadership.
A6: Task | B6: What to practice
A7: 1 | B7: Format the sales table with readable headers, currency, percentages, and dates.
A8: 2 | B8: Use Find & Replace to change region name 'West-Coast' to 'West'.
A9: 3 | B9: Use XLOOKUP/VLOOKUP to return each product category from the lookup table.
A10: 4 | B10: Calculate revenue, cost, profit, and profit margin.
A11: 5 | B11: Use IF to assign a review status: Review when profit margin is below 20%, otherwise OK.
A12: 6 | B12: Use SUMIF/COUNTIF to summarize revenue, profit, and review counts by region.
A13: 7 | B13: Preview the workbook before printing and adjust orientation/scaling if needed.
A16: Business question: Which region is generating the most revenue, and which orders need manager review because profit margin is too low?
A18: Solution
B19: =Exercise!A18 -> Region Summary | C19: =Exercise!B18 -> Revenue | D19: =Exercise!C18 -> Profit | E19: =Exercise!D18 -> Avg Margin | F19: =Exercise!E18 -> Review Orders
B20: =Exercise!A20 -> North | C20: =Exercise!B20 -> 8619 | D20: =Exercise!C20 -> 6264 | E20: =Exercise!D20 -> 0.030114348 | F20: =Exercise!E20 -> 1
B21: =Exercise!A21 -> South | C21: =Exercise!B21 -> 5575 | D21: =Exercise!C21 -> 3173 | E21: =Exercise!D21 -> 0.49045097 | F21: =Exercise!E21 -> 1
B22: =Exercise!A19 -> East | C22: =Exercise!B19 -> 5556 | D22: =Exercise!C19 -> 3079 | E22: =Exercise!D19 -> 0.56586628 | F22: =Exercise!E19 -> 0
B23: =Exercise!A22 -> West | C23: =Exercise!B22 -> 4135 | D23: =Exercise!C22 -> 2090 | E23: =Exercise!D22 -> 0.35831434 | F23: =Exercise!E22 -> 1
B24: =Exercise!A24 -> Total | C24: =Exercise!B24 -> 23885 | D24: =Exercise!C24 -> 14606 | E24: =Exercise!D24 -> 0.36118648 | F24: =Exercise!E24 -> 3

Sheet Sales Data
A1: Order ID | B1: Order Date | C1: Region | D1: Rep | E1: Product | F1: Category | G1: Units | H1: Unit Price | I1: Unit Cost | J1: Revenue | K1: Cost | L1: Profit | M1: Profit Margin | N1: Status | P1: Product | Q1: Category
A2: SO-1001 | B2: 46027 | C2: East | D2: A. Patel | E2: Laptop Stand | F2: Accessories | G2: 18 | H2: 77 | I2: 24 | J2: 1386 | K2: 432 | L2: 954 | M2: 0.68831169 | N2: Excellent | P2: Laptop Stand | Q2: Accessories
A3: SO-1002 | B3: 46029 | C3: West | D3: M. Chen | E3: Wireless Mouse | F3: Accessories | G3: 40 | H3: 38 | I3: 15 | J3: 1520 | K3: 600 | L3: 920 | M3: 0.60526316 | N3: Excellent | P3: Wireless Mouse | Q3: Accessories
A4: SO-1003 | B4: 46031 | C4: South | D4: J. Rivera | E4: USB-C Hub | F4: Connectivity | G4: 22 | H4: 113 | I4: 39 | J4: 2486 | K4: 858 | L4: 1628 | M4: 0.65486726 | N4: Excellent | P4: USB-C Hub | Q4: Connectivity
A5: SO-1004 | B5: 46034 | C5: North | D5: S. Brooks | E5: Monitor Arm | F5: Furniture | G5: 12 | H5: 34 | I5: 68 | J5: 408 | K5: 816 | L5: -408 | M5: -1 | N5: Good | P5: Monitor Arm | Q5: Furniture
A6: SO-1005 | B6: 46036 | C6: East | D6: A. Patel | E6: Keyboard | F6: Accessories | G6: 35 | H6: 48 | I6: 25 | J6: 1680 | K6: 875 | L6: 805 | M6: 0.47916667 | N6: Excellent | P6: Keyboard | Q6: Accessories
A7: SO-1006 | B7: 46038 | C7: West | D7: M. Chen | E7: Webcam | F7: Video | G7: 15 | H7: 135 | I7: 51 | J7: 2025 | K7: 765 | L7: 1260 | M7: 0.62222222 | N7: Excellent | P7: Webcam | Q7: Video
A8: SO-1007 | B8: 46040 | C8: South | D8: J. Rivera | E8: Docking Station | F8: Connectivity | G8: 8 | H8: 133 | I8: 118 | J8: 1064 | K8: 944 | L8: 120 | M8: 0.11278195 | N8: Good | P8: Docking Station | Q8: Connectivity
A9: SO-1008 | B9: 46043 | C9: North | D9: S. Brooks | E9: Wireless Mouse | F9: Accessories | G9: 55 | H9: 133 | I9: 15 | J9: 7315 | K9: 825 | L9: 6490 | M9: 0.88721805 | N9: Excellent
A10: SO-1009 | B10: 46045 | C10: East | D10: A. Patel | E10: USB-C Hub | F10: Connectivity | G10: 30 | H10: 83 | I10: 39 | J10: 2490 | K10: 1170 | L10: 1320 | M10: 0.53012048 | N10: Excellent
A11: SO-1010 | B11: 46047 | C11: West | D11: M. Chen | E11: Monitor Arm | F11: Furniture | G11: 10 | H11: 59 | I11: 68 | J11: 590 | K11: 680 | L11: -90 | M11: -0.15254237 | N11: Good
A12: SO-1011 | B12: 46049 | C12: South | D12: J. Rivera | E12: Laptop Stand | F12: Accessories | G12: 25 | H12: 81 | I12: 24 | J12: 2025 | K12: 600 | L12: 1425 | M12: 0.7037037 | N12: Excellent
A13: SO-1012 | B13: 46052 | C13: North | D13: S. Brooks | E13: Webcam | F13: Video | G13: 14 | H13: 64 | I13: 51 | J13: 896 | K13: 714 | L13: 182 | M13: 0.203125 | N13: Excellent
G17: Status
G18: Excellent | I18: Good | K18: Total Revenue | L18: Total Profit
F19: Region | G19: Revenue | H19: Profit | I19: Revenue | J19: Profit
F20: East | G20: 3826 | H20: 1349 | I20: 0 | J20: 0 | K20: 3826 | L20: 1349
F21: North | G21: 3551 | H21: 1196 | I21: 0 | J21: 0 | K21: 3551 | L21: 1196
F22: South | G22: 2326 | H22: 868 | I22: 1160 | J22: 216 | K22: 3486 | L22: 1084
F23: West | G23: 3060 | H23: 1015 | I23: 0 | J23: 0 | K23: 3060 | L23: 1015
F24: Grand Total | G24: 12763 | H24: 4428 | I24: 1160 | J24: 216 | K24: 13923 | L24: 4644

Sheet Exercise
A1: Complete the Formula Columns
A3: Order ID | B3: Order Date | C3: Region | D3: Rep | E3: Product | F3: Units | G3: Unit Price | H3: Unit Cost | I3: Category | J3: Revenue | K3: Profit | L3: Margin | M3: Status | O3: Formula help | P3: Example
A4: ='Sales Data'!A2 -> SO-1001 | B4: ='Sales Data'!B2 -> 46027 | C4: ='Sales Data'!C2 -> East | D4: ='Sales Data'!D2 -> A. Patel | E4: ='Sales Data'!E2 -> Laptop Stand | F4: ='Sales Data'!G2 -> 18 | G4: ='Sales Data'!H2 -> 77 | H4: ='Sales Data'!I2 -> 24 | I4: =_xlfn.XLOOKUP(E4,ProductLookupTable[Product],ProductLookupTable[Category]) -> Accessories | J4: =G4*F4 -> 1386 | K4: =J4-(H4*F4) -> 954 | L4: =K4/J4 -> 0.68831169 | M4: =IF(L4<0.2,"Review","OK") -> OK | O4: Category | P4: =XLOOKUP(E4,'Sales Data'!$J$2:$J$8,'Sales Data'!$K$2:$K$8)
A5: ='Sales Data'!A3 -> SO-1002 | B5: ='Sales Data'!B3 -> 46029 | C5: ='Sales Data'!C3 -> West | D5: ='Sales Data'!D3 -> M. Chen | E5: ='Sales Data'!E3 -> Wireless Mouse | F5: ='Sales Data'!G3 -> 40 | G5: ='Sales Data'!H3 -> 38 | H5: ='Sales Data'!I3 -> 15 | I5: =_xlfn.XLOOKUP(E5,ProductLookupTable[Product],ProductLookupTable[Category]) -> Accessories | J5: =G5*F5 -> 1520 | K5: =J5-(H5*F5) -> 920 | L5: =K5/J5 -> 0.60526316 | M5: =IF(L5<0.2,"Review","OK") -> OK | O5: Revenue | P5: =F4*G4
A6: ='Sales Data'!A4 -> SO-1003 | B6: ='Sales Data'!B4 -> 46031 | C6: ='Sales Data'!C4 -> South | D6: ='Sales Data'!D4 -> J. Rivera | E6: ='Sales Data'!E4 -> USB-C Hub | F6: ='Sales Data'!G4 -> 22 | G6: ='Sales Data'!H4 -> 113 | H6: ='Sales Data'!I4 -> 39 | I6: =_xlfn.XLOOKUP(E6,ProductLookupTable[Product],ProductLookupTable[Category]) -> Connectivity | J6: =G6*F6 -> 2486 | K6: =J6-(H6*F6) -> 1628 | L6: =K6/J6 -> 0.65486726 | M6: =IF(L6<0.2,"Review","OK") -> OK | O6: Profit | P6: =J4-(F4*H4)
A7: ='Sales Data'!A5 -> SO-1004 | B7: ='Sales Data'!B5 -> 46034 | C7: ='Sales Data'!C5 -> North | D7: ='Sales Data'!D5 -> S. Brooks | E7: ='Sales Data'!E5 -> Monitor Arm | F7: ='Sales Data'!G5 -> 12 | G7: ='Sales Data'!H5 -> 34 | H7: ='Sales Data'!I5 -> 68 | I7: =_xlfn.XLOOKUP(E7,ProductLookupTable[Product],ProductLookupTable[Category]) -> Furniture | J7: =G7*F7 -> 408 | K7: =J7-(H7*F7) -> -408 | L7: =K7/J7 -> -1 | M7: =IF(L7<0.2,"Review","OK") -> Review | O7: Margin | P7: =K4/J4
A8: ='Sales Data'!A6 -> SO-1005 | B8: ='Sales Data'!B6 -> 46036 | C8: ='Sales Data'!C6 -> East | D8: ='Sales Data'!D6 -> A. Patel | E8: ='Sales Data'!E6 -> Keyboard | F8: ='Sales Data'!G6 -> 35 | G8: ='Sales Data'!H6 -> 48 | H8: ='Sales Data'!I6 -> 25 | I8: =_xlfn.XLOOKUP(E8,ProductLookupTable[Product],ProductLookupTable[Category]) -> Accessories | J8: =G8*F8 -> 1680 | K8: =J8-(H8*F8) -> 805 | L8: =K8/J8 -> 0.47916667 | M8: =IF(L8<0.2,"Review","OK") -> OK | O8: Status | P8: =IF(L4<20%,"Review","OK")
A9: ='Sales Data'!A7 -> SO-1006 | B9: ='Sales Data'!B7 -> 46038 | C9: ='Sales Data'!C7 -> West | D9: ='Sales Data'!D7 -> M. Chen | E9: ='Sales Data'!E7 -> Webcam | F9: ='Sales Data'!G7 -> 15 | G9: ='Sales Data'!H7 -> 135 | H9: ='Sales Data'!I7 -> 51 | I9: =_xlfn.XLOOKUP(E9,ProductLookupTable[Product],ProductLookupTable[Category]) -> Video | J9: =G9*F9 -> 2025 | K9: =J9-(H9*F9) -> 1260 | L9: =K9/J9 -> 0.62222222 | M9: =IF(L9<0.2,"Review","OK") -> OK
A10: ='Sales Data'!A8 -> SO-1007 | B10: ='Sales Data'!B8 -> 46040 | C10: ='Sales Data'!C8 -> South | D10: ='Sales Data'!D8 -> J. Rivera | E10: ='Sales Data'!E8 -> Docking Station | F10: ='Sales Data'!G8 -> 8 | G10: ='Sales Data'!H8 -> 133 | H10: ='Sales Data'!I8 -> 118 | I10: =_xlfn.XLOOKUP(E10,ProductLookupTable[Product],ProductLookupTable[Category]) -> Connectivity | J10: =G10*F10 -> 1064 | K10: =J10-(H10*F10) -> 120 | L10: =K10/J10 -> 0.11278195 | M10: =IF(L10<0.2,"Review","OK") -> Review
A11: ='Sales Data'!A9 -> SO-1008 | B11: ='Sales Data'!B9 -> 46043 | C11: ='Sales Data'!C9 -> North | D11: ='Sales Data'!D9 -> S. Brooks | E11: ='Sales Data'!E9 -> Wireless Mouse | F11: ='Sales Data'!G9 -> 55 | G11: ='Sales Data'!H9 -> 133 | H11: ='Sales Data'!I9 -> 15 | I11: =_xlfn.XLOOKUP(E11,ProductLookupTable[Product],ProductLookupTable[Category]) -> Accessories | J11: =G11*F11 -> 7315 | K11: =J11-(H11*F11) -> 6490 | L11: =K11/J11 -> 0.88721805 | M11: =IF(L11<0.2,"Review","OK") -> OK
A12: ='Sales Data'!A10 -> SO-1009 | B12: ='Sales Data'!B10 -> 46045 | C12: ='Sales Data'!C10 -> East | D12: ='Sales Data'!D10 -> A. Patel | E12: ='Sales Data'!E10 -> USB-C Hub | F12: ='Sales Data'!G10 -> 30 | G12: ='Sales Data'!H10 -> 83 | H12: ='Sales Data'!I10 -> 39 | I12: =_xlfn.XLOOKUP(E12,ProductLookupTable[Product],ProductLookupTable[Category]) -> Connectivity | J12: =G12*F12 -> 2490 | K12: =J12-(H12*F12) -> 1320 | L12: =K12/J12 -> 0.53012048 | M12: =IF(L12<0.2,"Review","OK") -> OK
A13: ='Sales Data'!A11 -> SO-1010 | B13: ='Sales Data'!B11 -> 46047 | C13: ='Sales Data'!C11 -> West | D13: ='Sales Data'!D11 -> M. Chen | E13: ='Sales Data'!E11 -> Monitor Arm | F13: ='Sales Data'!G11 -> 10 | G13: ='Sales Data'!H11 -> 59 | H13: ='Sales Data'!I11 -> 68 | I13: =_xlfn.XLOOKUP(E13,ProductLookupTable[Product],ProductLookupTable[Category]) -> Furniture | J13: =G13*F13 -> 590 | K13: =J13-(H13*F13) -> -90 | L13: =K13/J13 -> -0.15254237 | M13: =IF(L13<0.2,"Review","OK") -> Review
A14: ='Sales Data'!A12 -> SO-1011 | B14: ='Sales Data'!B12 -> 46049 | C14: ='Sales Data'!C12 -> South | D14: ='Sales Data'!D12 -> J. Rivera | E14: ='Sales Data'!E12 -> Laptop Stand | F14: ='Sales Data'!G12 -> 25 | G14: ='Sales Data'!H12 -> 81 | H14: ='Sales Data'!I12 -> 24 | I14: =_xlfn.XLOOKUP(E14,ProductLookupTable[Product],ProductLookupTable[Category]) -> Accessories | J14: =G14*F14 -> 2025 | K14: =J14-(H14*F14) -> 1425 | L14: =K14/J14 -> 0.7037037 | M14: =IF(L14<0.2,"Review","OK") -> OK
A15: ='Sales Data'!A13 -> SO-1012 | B15: ='Sales Data'!B13 -> 46052 | C15: ='Sales Data'!C13 -> North | D15: ='Sales Data'!D13 -> S. Brooks | E15: ='Sales Data'!E13 -> Webcam | F15: ='Sales Data'!G13 -> 14 | G15: ='Sales Data'!H13 -> 64 | H15: ='Sales Data'!I13 -> 51 | I15: =_xlfn.XLOOKUP(E15,ProductLookupTable[Product],ProductLookupTable[Category]) -> Video | J15: =G15*F15 -> 896 | K15: =J15-(H15*F15) -> 182 | L15: =K15/J15 -> 0.203125 | M15: =IF(L15<0.2,"Review","OK") -> OK
A18: Region Summary | B18: Revenue | C18: Profit | D18: Avg Margin | E18: Review Orders | H18: KPI | I18: Output
A19: East | B19: =SUMIF($C$4:$C$15,A19,$J$4:$J$15) -> 5556 | C19: =SUMIF($C$4:$C$15,A19,$K$4:$K$15) -> 3079 | D19: =AVERAGEIF($C$4:$C$15,A19,$L$4:$L$15) -> 0.56586628 | E19: =COUNTIFS($C$4:$C$15,A19,$M$4:$M$15,"Review") -> 0 | H19: Top Revenuer Region | I19: =_xlfn.XLOOKUP(MAX($B$19:$B$22),$B$19:$B$22,$A$19:$A$22) -> North
A20: North | B20: =SUMIF($C$4:$C$15,A20,$J$4:$J$15) -> 8619 | C20: =SUMIF($C$4:$C$15,A20,$K$4:$K$15) -> 6264 | D20: =AVERAGEIF($C$4:$C$15,A20,$L$4:$L$15) -> 0.030114348 | E20: =COUNTIFS($C$4:$C$15,A20,$M$4:$M$15,"Review") -> 1 | H20: Highest Margin Region | I20: =_xlfn.XLOOKUP( MAX($D$19:$D$22),$D$19:$D$22,$A$19:$A$22) -> East
A21: South | B21: =SUMIF($C$4:$C$15,A21,$J$4:$J$15) -> 5575 | C21: =SUMIF($C$4:$C$15,A21,$K$4:$K$15) -> 3173 | D21: =AVERAGEIF($C$4:$C$15,A21,$L$4:$L$15) -> 0.49045097 | E21: =COUNTIFS($C$4:$C$15,A21,$M$4:$M$15,"Review") -> 1 | H21: Orders to review | I21: =SUM(E19:E22) -> 3
A22: West | B22: =SUMIF($C$4:$C$15,A22,$J$4:$J$15) -> 4135 | C22: =SUMIF($C$4:$C$15,A22,$K$4:$K$15) -> 2090 | D22: =AVERAGEIF($C$4:$C$15,A22,$L$4:$L$15) -> 0.35831434 | E22: =COUNTIFS($C$4:$C$15,A22,$M$4:$M$15,"Review") -> 1 | H22: Highest Margin | I22: =MAX(D19:D22) -> 0.56586628
A24: Total | B24: =SUM(B19:B22) -> 23885 | C24: =SUM(C19:C22) -> 14606 | D24: =AVERAGE($D$19:$D$22) -> 0.36118648 | E24: =SUM(E19:E22) -> 3
